README.md
setup.py
gcmc/__init__.py
gcmc/base.py
gcmc/dataset.py
gcmc/files.py
gcmc/gcmc.cpp
gcmc/gcmc.cu
gcmc/gcmc.h
gcmc/gcmc.py
gcmc/gcmc_energy.h
gcmc/gcmc_move.h
gcmc/gcmc_move_add.h
gcmc/gcmc_move_del.h
gcmc/gcmc_move_rot.h
gcmc/gcmc_move_trn.h
gcmc/main.py
gcmc/mainOld.py
gcmc/packages.py
gcmc/parameters.py
gcmc/protein_data.py
gcmc/resources.zip
gcmc/simulation.py
gcmc/toppar.str
gcmc/values.py
gcmc/charmm36.ff/atomtypes.atp
gcmc/charmm36.ff/cmap.itp
gcmc/charmm36.ff/ffbonded.itp
gcmc/charmm36.ff/ffnonbonded.itp
gcmc/charmm36.ff/forcefield.doc
gcmc/charmm36.ff/forcefield.itp
gcmc/charmm36.ff/gb.itp
gcmc/charmm36.ff/ic_info.txt
gcmc/charmm36.ff/ions.itp
gcmc/charmm36.ff/merged.arn
gcmc/charmm36.ff/merged.c.tdb
gcmc/charmm36.ff/merged.hdb
gcmc/charmm36.ff/merged.n.tdb
gcmc/charmm36.ff/merged.r2b
gcmc/charmm36.ff/merged.rtp
gcmc/charmm36.ff/merged.vsd
gcmc/charmm36.ff/nbfix.itp
gcmc/charmm36.ff/old_c36_cmap.itp
gcmc/charmm36.ff/radii.txt
gcmc/charmm36.ff/residuetypes.dat
gcmc/charmm36.ff/silcs.itp
gcmc/charmm36.ff/spc.itp
gcmc/charmm36.ff/spce.itp
gcmc/charmm36.ff/specbond.dat
gcmc/charmm36.ff/tip3p.itp
gcmc/charmm36.ff/tip3p_2.itp
gcmc/charmm36.ff/tip4p.itp
gcmc/charmm36.ff/watermodels.dat
gcmc/charmm36.ff/mol/aald.itp
gcmc/charmm36.ff/mol/aald.pdb
gcmc/charmm36.ff/mol/acet.itp
gcmc/charmm36.ff/mol/acet.pdb
gcmc/charmm36.ff/mol/acey.itp
gcmc/charmm36.ff/mol/acey.pdb
gcmc/charmm36.ff/mol/acox.itp
gcmc/charmm36.ff/mol/acox.pdb
gcmc/charmm36.ff/mol/anil.itp
gcmc/charmm36.ff/mol/anil.pdb
gcmc/charmm36.ff/mol/benx.itp
gcmc/charmm36.ff/mol/benx.pdb
gcmc/charmm36.ff/mol/benz.itp
gcmc/charmm36.ff/mol/benz.pdb
gcmc/charmm36.ff/mol/brbx.itp
gcmc/charmm36.ff/mol/brbx.pdb
gcmc/charmm36.ff/mol/brob.itp
gcmc/charmm36.ff/mol/brob.pdb
gcmc/charmm36.ff/mol/cal.itp
gcmc/charmm36.ff/mol/cal.pdb
gcmc/charmm36.ff/mol/caly.itp
gcmc/charmm36.ff/mol/caly.pdb
gcmc/charmm36.ff/mol/chlb.itp
gcmc/charmm36.ff/mol/chlb.pdb
gcmc/charmm36.ff/mol/cla.itp
gcmc/charmm36.ff/mol/cla.pdb
pyGCMC.egg-info/PKG-INFO
pyGCMC.egg-info/SOURCES.txt
pyGCMC.egg-info/dependency_links.txt
pyGCMC.egg-info/entry_points.txt
pyGCMC.egg-info/requires.txt
pyGCMC.egg-info/top_level.txt