Metadata-Version: 2.1
Name: pyGCMC
Version: 1.1.240324
